[{"rallyid":1,"server":"Rudy Quan","x":36.0,"y":-206.0,"serveIn":true,"side":"Deuce","serveInPlacement":"T","pointWonByUCLA":true,"isAce":null,"serveResult":"1st Serve In","firstOrSecServe":"1st Serve"},{"rallyid":2,"server":"Rudy Quan","x":-71.0,"y":-193.0,"serveIn":true,"side":"Ad","serveInPlacement":"Body","pointWonByUCLA":false,"isAce":null,"serveResult":"1st Serve In","firstOrSecServe":"1st Serve"},{"rallyid":3,"server":"Rudy Quan","x":113.0,"y":-182.0,"serveIn":true,"side":"Deuce","serveInPlacement":"Wide","pointWonByUCLA":false,"isAce":null,"serveResult":"1st Serve In","firstOrSecServe":"1st Serve"},{"rallyid":4,"server":"Rudy Quan","x":-47.0,"y":-227.0,"serveIn":true,"side":"Ad","serveInPlacement":"T","pointWonByUCLA":true,"isAce":null,"serveResult":"1st Serve In","firstOrSecServe":"1st Serve"},{"rallyid":5,"server":"Rudy Quan","x":41.0,"y":-233.0,"serveIn":true,"side":"Deuce","serveInPlacement":"T","pointWonByUCLA":true,"isAce":null,"serveResult":"1st Serve In","firstOrSecServe":"1st Serve"},{"rallyid":6,"server":"Rudy Quan","x":-84.0,"y":-211.0,"serveIn":true,"side":"Ad","serveInPlacement":"Body","pointWonByUCLA":true,"isAce":null,"serveResult":"1st Serve In","firstOrSecServe":"1st Serve"},{"rallyid":13,"server":"Rudy Quan","x":47.0,"y":-191.0,"serveIn":true,"side":"Deuce","serveInPlacement":"T","pointWonByUCLA":false,"isAce":null,"serveResult":"2nd Serve In","firstOrSecServe":"2nd Serve"},{"rallyid":14,"server":"Rudy Quan","x":-70.0,"y":-159.0,"serveIn":true,"side":"Ad","serveInPlacement":"Body","pointWonByUCLA":true,"isAce":null,"serveResult":"1st Serve In","firstOrSecServe":"1st Serve"},{"rallyid":15,"server":"Rudy Quan","x":71.0,"y":-215.0,"serveIn":true,"side":"Deuce","serveInPlacement":"Body","pointWonByUCLA":false,"isAce":null,"serveResult":"1st Serve In","firstOrSecServe":"1st Serve"},{"rallyid":16,"server":"Rudy Quan","x":-105.0,"y":-154.0,"serveIn":true,"side":"Ad","serveInPlacement":"Body","pointWonByUCLA":true,"isAce":null,"serveResult":"2nd Serve In","firstOrSecServe":"2nd Serve"},{"rallyid":17,"server":"Rudy Quan","x":74.0,"y":-218.0,"serveIn":true,"side":"Deuce","serveInPlacement":"Body","pointWonByUCLA":true,"isAce":null,"serveResult":"1st Serve In","firstOrSecServe":"1st Serve"},{"rallyid":18,"server":"Rudy Quan","x":-110.0,"y":-186.0,"serveIn":true,"side":"Ad","serveInPlacement":"Wide","pointWonByUCLA":true,"isAce":null,"serveResult":"1st Serve In","firstOrSecServe":"1st Serve"},{"rallyid":25,"server":"Rudy Quan","x":42.0,"y":-230.0,"serveIn":true,"side":"Deuce","serveInPlacement":"T","pointWonByUCLA":false,"isAce":null,"serveResult":"1st Serve In","firstOrSecServe":"1st Serve"},{"rallyid":26,"server":"Rudy Quan","x":-57.0,"y":-225.0,"serveIn":true,"side":"Ad","serveInPlacement":"Body","pointWonByUCLA":false,"isAce":null,"serveResult":"1st Serve In","firstOrSecServe":"1st Serve"},{"rallyid":27,"server":"Rudy Quan","x":37.0,"y":-241.0,"serveIn":true,"side":"Deuce","serveInPlacement":"T","pointWonByUCLA":true,"isAce":null,"serveResult":"1st Serve In","firstOrSecServe":"1st Serve"},{"rallyid":28,"server":"Rudy Quan","x":-78.0,"y":-201.0,"serveIn":true,"side":"Ad","serveInPlacement":"Body","pointWonByUCLA":false,"isAce":null,"serveResult":"1st Serve In","firstOrSecServe":"1st Serve"},{"rallyid":29,"server":"Rudy Quan","x":37.0,"y":-233.0,"serveIn":true,"side":"Deuce","serveInPlacement":"T","pointWonByUCLA":false,"isAce":null,"serveResult":"1st Serve In","firstOrSecServe":"1st Serve"},{"rallyid":30,"server":"Rudy Quan","x":-91.0,"y":-230.0,"serveIn":true,"side":"Ad","serveInPlacement":"Body","pointWonByUCLA":true,"isAce":null,"serveResult":"1st Serve In","firstOrSecServe":"1st Serve"},{"rallyid":36,"server":"Rudy Quan","x":89.0,"y":-86.0,"serveIn":true,"side":"Deuce","serveInPlacement":"Body","pointWonByUCLA":false,"isAce":null,"serveResult":"1st Serve In","firstOrSecServe":"1st Serve"},{"rallyid":37,"server":"Rudy Quan","x":-76.0,"y":-118.0,"serveIn":true,"side":"Ad","serveInPlacement":"Body","pointWonByUCLA":false,"isAce":null,"serveResult":"1st Serve In","firstOrSecServe":"1st Serve"},{"rallyid":38,"server":"Rudy Quan","x":54.0,"y":-99.0,"serveIn":true,"side":"Deuce","serveInPlacement":"Body","pointWonByUCLA":true,"isAce":null,"serveResult":"2nd Serve In","firstOrSecServe":"2nd Serve"},{"rallyid":39,"server":"Rudy Quan","x":-79.0,"y":-83.0,"serveIn":true,"side":"Ad","serveInPlacement":"Body","pointWonByUCLA":true,"isAce":null,"serveResult":"2nd Serve In","firstOrSecServe":"2nd Serve"},{"rallyid":40,"server":"Rudy Quan","x":81.0,"y":-110.0,"serveIn":true,"side":"Deuce","serveInPlacement":"Body","pointWonByUCLA":false,"isAce":null,"serveResult":"2nd Serve In","firstOrSecServe":"2nd Serve"},{"rallyid":41,"server":"Rudy Quan","x":-39.0,"y":-156.0,"serveIn":true,"side":"Ad","serveInPlacement":"T","pointWonByUCLA":true,"isAce":null,"serveResult":"1st Serve In","firstOrSecServe":"1st Serve"},{"rallyid":47,"server":"Rudy Quan","x":36.0,"y":-159.0,"serveIn":true,"side":"Deuce","serveInPlacement":"T","pointWonByUCLA":true,"isAce":null,"serveResult":"1st Serve In","firstOrSecServe":"1st Serve"},{"rallyid":48,"server":"Rudy Quan","x":-97.0,"y":-133.0,"serveIn":true,"side":"Ad","serveInPlacement":"Body","pointWonByUCLA":true,"isAce":null,"serveResult":"1st Serve In","firstOrSecServe":"1st Serve"},{"rallyid":49,"server":"Rudy Quan","x":50.0,"y":-149.0,"serveIn":true,"side":"Deuce","serveInPlacement":"T","pointWonByUCLA":false,"isAce":null,"serveResult":"2nd Serve In","firstOrSecServe":"2nd Serve"},{"rallyid":50,"server":"Rudy Quan","x":-105.0,"y":-151.0,"serveIn":true,"side":"Ad","serveInPlacement":"Body","pointWonByUCLA":true,"isAce":null,"serveResult":"1st Serve In","firstOrSecServe":"1st Serve"},{"rallyid":51,"server":"Rudy Quan","x":39.0,"y":-130.0,"serveIn":true,"side":"Deuce","serveInPlacement":"T","pointWonByUCLA":false,"isAce":null,"serveResult":"2nd Serve In","firstOrSecServe":"2nd Serve"},{"rallyid":52,"server":"Rudy Quan","x":-86.0,"y":-159.0,"serveIn":true,"side":"Ad","serveInPlacement":"Body","pointWonByUCLA":true,"isAce":null,"serveResult":"1st Serve In","firstOrSecServe":"1st Serve"},{"rallyid":60,"server":"Rudy Quan","x":76.0,"y":-218.0,"serveIn":true,"side":"Deuce","serveInPlacement":"Body","pointWonByUCLA":false,"isAce":null,"serveResult":"1st Serve In","firstOrSecServe":"1st Serve"},{"rallyid":61,"server":"Rudy Quan","x":-82.0,"y":-211.0,"serveIn":true,"side":"Ad","serveInPlacement":"Body","pointWonByUCLA":true,"isAce":null,"serveResult":"2nd Serve In","firstOrSecServe":"2nd Serve"},{"rallyid":62,"server":"Rudy Quan","x":38.0,"y":-233.0,"serveIn":true,"side":"Deuce","serveInPlacement":"T","pointWonByUCLA":true,"isAce":null,"serveResult":"1st Serve In","firstOrSecServe":"1st Serve"},{"rallyid":63,"server":"Rudy Quan","x":-108.0,"y":-216.0,"serveIn":true,"side":"Ad","serveInPlacement":"Wide","pointWonByUCLA":true,"isAce":null,"serveResult":"1st Serve In","firstOrSecServe":"1st Serve"},{"rallyid":64,"server":"Rudy Quan","x":21.0,"y":-227.0,"serveIn":true,"side":"Deuce","serveInPlacement":"T","pointWonByUCLA":false,"isAce":null,"serveResult":"1st Serve In","firstOrSecServe":"1st Serve"},{"rallyid":65,"server":"Rudy Quan","x":-123.0,"y":-221.0,"serveIn":true,"side":"Ad","serveInPlacement":"Wide","pointWonByUCLA":false,"isAce":null,"serveResult":"1st Serve In","firstOrSecServe":"1st Serve"},{"rallyid":66,"server":"Rudy Quan","x":90.0,"y":-213.0,"serveIn":true,"side":"Deuce","serveInPlacement":"Body","pointWonByUCLA":false,"isAce":null,"serveResult":"1st Serve In","firstOrSecServe":"1st Serve"},{"rallyid":73,"server":"Rudy Quan","x":87.0,"y":-214.0,"serveIn":true,"side":"Deuce","serveInPlacement":"Body","pointWonByUCLA":false,"isAce":null,"serveResult":"1st Serve In","firstOrSecServe":"1st Serve"},{"rallyid":74,"server":"Rudy Quan","x":-87.0,"y":-240.0,"serveIn":true,"side":"Ad","serveInPlacement":"Body","pointWonByUCLA":true,"isAce":null,"serveResult":"1st Serve In","firstOrSecServe":"1st Serve"},{"rallyid":75,"server":"Rudy Quan","x":28.0,"y":-219.0,"serveIn":true,"side":"Deuce","serveInPlacement":"T","pointWonByUCLA":false,"isAce":null,"serveResult":"1st Serve In","firstOrSecServe":"1st Serve"},{"rallyid":76,"server":"Rudy Quan","x":-127.0,"y":-216.0,"serveIn":true,"side":"Ad","serveInPlacement":"Wide","pointWonByUCLA":true,"isAce":null,"serveResult":"1st Serve In","firstOrSecServe":"1st Serve"},{"rallyid":77,"server":"Rudy Quan","x":84.0,"y":-216.0,"serveIn":true,"side":"Deuce","serveInPlacement":"Body","pointWonByUCLA":false,"isAce":null,"serveResult":"1st Serve In","firstOrSecServe":"1st Serve"},{"rallyid":84,"server":"Rudy Quan","x":79.0,"y":-200.0,"serveIn":true,"side":"Deuce","serveInPlacement":"Body","pointWonByUCLA":false,"isAce":null,"serveResult":"2nd Serve In","firstOrSecServe":"2nd Serve"},{"rallyid":85,"server":"Rudy Quan","x":-69.0,"y":-227.0,"serveIn":true,"side":"Ad","serveInPlacement":"Body","pointWonByUCLA":true,"isAce":null,"serveResult":"1st Serve In","firstOrSecServe":"1st Serve"},{"rallyid":86,"server":"Rudy Quan","x":73.0,"y":-208.0,"serveIn":true,"side":"Deuce","serveInPlacement":"Body","pointWonByUCLA":false,"isAce":null,"serveResult":"2nd Serve In","firstOrSecServe":"2nd Serve"},{"rallyid":87,"server":"Rudy Quan","x":-77.0,"y":-229.0,"serveIn":true,"side":"Ad","serveInPlacement":"Body","pointWonByUCLA":true,"isAce":null,"serveResult":"2nd Serve In","firstOrSecServe":"2nd Serve"},{"rallyid":88,"server":"Rudy Quan","x":70.0,"y":-216.0,"serveIn":true,"side":"Deuce","serveInPlacement":"Body","pointWonByUCLA":false,"isAce":null,"serveResult":"1st Serve In","firstOrSecServe":"1st Serve"},{"rallyid":89,"server":"Rudy Quan","x":-127.0,"y":-216.0,"serveIn":true,"side":"Ad","serveInPlacement":"Wide","pointWonByUCLA":false,"isAce":null,"serveResult":"1st Serve In","firstOrSecServe":"1st Serve"},{"rallyid":94,"server":"Rudy Quan","x":58.0,"y":-152.0,"serveIn":true,"side":"Deuce","serveInPlacement":"Body","pointWonByUCLA":false,"isAce":null,"serveResult":"2nd Serve In","firstOrSecServe":"2nd Serve"},{"rallyid":95,"server":"Rudy Quan","x":-97.0,"y":-220.0,"serveIn":true,"side":"Ad","serveInPlacement":"Body","pointWonByUCLA":true,"isAce":null,"serveResult":"1st Serve In","firstOrSecServe":"1st Serve"},{"rallyid":96,"server":"Rudy Quan","x":76.0,"y":-233.0,"serveIn":true,"side":"Deuce","serveInPlacement":"Body","pointWonByUCLA":false,"isAce":null,"serveResult":"1st Serve In","firstOrSecServe":"1st Serve"},{"rallyid":97,"server":"Rudy Quan","x":-78.0,"y":-169.0,"serveIn":true,"side":"Ad","serveInPlacement":"Body","pointWonByUCLA":false,"isAce":null,"serveResult":"1st Serve In","firstOrSecServe":"1st Serve"},{"rallyid":98,"server":"Rudy Quan","x":44.0,"y":-145.0,"serveIn":true,"side":"Deuce","serveInPlacement":"T","pointWonByUCLA":true,"isAce":null,"serveResult":"1st Serve In","firstOrSecServe":"1st Serve"},{"rallyid":99,"server":"Rudy Quan","x":-81.0,"y":-137.0,"serveIn":true,"side":"Ad","serveInPlacement":"Body","pointWonByUCLA":false,"isAce":null,"serveResult":"1st Serve In","firstOrSecServe":"1st Serve"},{"rallyid":106,"server":"Rudy Quan","x":60.0,"y":-172.0,"serveIn":true,"side":"Deuce","serveInPlacement":"Body","pointWonByUCLA":true,"isAce":null,"serveResult":"1st Serve In","firstOrSecServe":"1st Serve"},{"rallyid":107,"server":"Rudy Quan","x":-79.0,"y":-100.0,"serveIn":true,"side":"Ad","serveInPlacement":"Body","pointWonByUCLA":true,"isAce":null,"serveResult":"2nd Serve In","firstOrSecServe":"2nd Serve"},{"rallyid":108,"server":"Rudy Quan","x":46.0,"y":-220.0,"serveIn":true,"side":"Deuce","serveInPlacement":"T","pointWonByUCLA":true,"isAce":null,"serveResult":"1st Serve In","firstOrSecServe":"1st Serve"},{"rallyid":109,"server":"Rudy Quan","x":-84.0,"y":-220.0,"serveIn":true,"side":"Ad","serveInPlacement":"Body","pointWonByUCLA":true,"isAce":null,"serveResult":"1st Serve In","firstOrSecServe":"1st Serve"},{"rallyid":117,"server":"Rudy Quan","x":36.0,"y":-116.0,"serveIn":true,"side":"Deuce","serveInPlacement":"T","pointWonByUCLA":false,"isAce":null,"serveResult":"1st Serve In","firstOrSecServe":"1st Serve"},{"rallyid":118,"server":"Rudy Quan","x":-102.0,"y":-142.0,"serveIn":true,"side":"Ad","serveInPlacement":"Body","pointWonByUCLA":true,"isAce":null,"serveResult":"1st Serve In","firstOrSecServe":"1st Serve"},{"rallyid":119,"server":"Rudy Quan","x":55.0,"y":-116.0,"serveIn":true,"side":"Deuce","serveInPlacement":"Body","pointWonByUCLA":false,"isAce":null,"serveResult":"2nd Serve In","firstOrSecServe":"2nd Serve"},{"rallyid":120,"server":"Rudy Quan","x":-86.0,"y":-177.0,"serveIn":true,"side":"Ad","serveInPlacement":"Body","pointWonByUCLA":false,"isAce":null,"serveResult":"1st Serve In","firstOrSecServe":"1st Serve"},{"rallyid":121,"server":"Rudy Quan","x":108.0,"y":-92.0,"serveIn":true,"side":"Deuce","serveInPlacement":"Wide","pointWonByUCLA":false,"isAce":null,"serveResult":"1st Serve In","firstOrSecServe":"1st Serve"},{"rallyid":122,"server":"Rudy Quan","x":-68.0,"y":-158.0,"serveIn":true,"side":"Ad","serveInPlacement":"Body","pointWonByUCLA":true,"isAce":null,"serveResult":"2nd Serve In","firstOrSecServe":"2nd Serve"},{"rallyid":123,"server":"Rudy Quan","x":58.0,"y":-172.0,"serveIn":true,"side":"Deuce","serveInPlacement":"Body","pointWonByUCLA":true,"isAce":null,"serveResult":"1st Serve In","firstOrSecServe":"1st Serve"}]